Metadata-Version: 2.1
Name: GGLogger
Version: 1.0.0
Summary: A simple function logger for Python
Home-page: https://github.com/Dmunch04/GGLogger
Author: Munchii
Author-email: contact@munchii.me
License: MIT
Keywords: simple function logger for python
Platform: UNKNOWN
Classifier: Development Status :: 4 - Beta
Classifier: Intended Audience :: End Users/Desktop
Classifier: Intended Audience :: Developers
Classifier: License :: OSI Approved :: MIT License
Classifier: Programming Language :: Python :: 3
Classifier: Operating System :: OS Independent
